Metadata-Version: 2.1
Name: sipprverse
Version: 0.2.49
Summary: Object oriented raw read typing software
Home-page: https://github.com/OLC-Bioinformatics/sipprverse
Author: Adam Koziol
Author-email: adam.koziol@canada.ca
License: MIT
Platform: UNKNOWN
License-File: LICENSE
